yvtools/__init__.py
yvtools/FlaskManage/__init__.py
yvtools/FlaskManage/manager.py
yvtools/Yvapp/__init__.py
yvtools/Yvapp/newApp.py
yvflask-1.0.2.dist-info/METADATA
yvflask-1.0.2.dist-info/WHEEL
yvflask-1.0.2.dist-info/top_level.txt
yvflask-1.0.2.dist-info/RECORD
