Metadata-Version: 2.1
Name: yvflask
Version: 1.0.2
Summary: This is a sample package
Author: YveRadvir
Author-email: Yveradvirr@gmail.com
Classifier: Development Status :: 3 - Alpha
Classifier: Intended Audience :: Developers
Classifier: License :: OSI Approved :: MIT License
Classifier: Programming Language :: Python :: 3
Classifier: Programming Language :: Python :: 3.9
